{"v":3,"stories":{"configure-your-project--docs":{"id":"configure-your-project--docs","title":"Configure your project","name":"Docs","importPath":"./src/stories/Configure.mdx","storiesImports":[],"tags":["unattached-mdx","docs"],"kind":"Configure your project","story":"Docs","parameters":{"__id":"configure-your-project--docs","docsOnly":true,"fileName":"./src/stories/Configure.mdx"}},"components-icon-button--default":{"id":"components-icon-button--default","name":"Default","title":"Components/Icon Button","importPath":"./src/IconButton/IconButton.stories.jsx","tags":["story"],"kind":"Components/Icon Button","story":"Default","parameters":{"__id":"components-icon-button--default","docsOnly":false,"fileName":"./src/IconButton/IconButton.stories.jsx"}},"components-icon-button--disabled":{"id":"components-icon-button--disabled","name":"Disabled","title":"Components/Icon Button","importPath":"./src/IconButton/IconButton.stories.jsx","tags":["story"],"kind":"Components/Icon Button","story":"Disabled","parameters":{"__id":"components-icon-button--disabled","docsOnly":false,"fileName":"./src/IconButton/IconButton.stories.jsx"}},"components-tooltip--default":{"id":"components-tooltip--default","name":"Default","title":"Components/Tooltip","importPath":"./src/Tooltip/Tooltip.stories.jsx","tags":["story"],"kind":"Components/Tooltip","story":"Default","parameters":{"__id":"components-tooltip--default","docsOnly":false,"fileName":"./src/Tooltip/Tooltip.stories.jsx"}},"design-system-colors--all-colors":{"id":"design-system-colors--all-colors","name":"All Colors","title":"Design System/Colors","importPath":"./src/colors/colors.stories.jsx","tags":["story"],"kind":"Design System/Colors","story":"All Colors","parameters":{"__id":"design-system-colors--all-colors","docsOnly":false,"fileName":"./src/colors/colors.stories.jsx"}},"components-input--with-placeholder":{"id":"components-input--with-placeholder","name":"With Placeholder","title":"Components/Input","importPath":"./src/input/customInput.stories.jsx","tags":["story"],"kind":"Components/Input","story":"With Placeholder","parameters":{"__id":"components-input--with-placeholder","docsOnly":false,"fileName":"./src/input/customInput.stories.jsx"}},"components-input--with-text":{"id":"components-input--with-text","name":"With Text","title":"Components/Input","importPath":"./src/input/customInput.stories.jsx","tags":["story"],"kind":"Components/Input","story":"With Text","parameters":{"__id":"components-input--with-text","docsOnly":false,"fileName":"./src/input/customInput.stories.jsx"}},"components-logo--promodoro-logo":{"id":"components-logo--promodoro-logo","name":"Promodoro Logo","title":"Components/logo","importPath":"./src/logo/logo.stories.jsx","tags":["story"],"kind":"Components/logo","story":"Promodoro Logo","parameters":{"__id":"components-logo--promodoro-logo","docsOnly":false,"fileName":"./src/logo/logo.stories.jsx"}},"components-navbar--default":{"id":"components-navbar--default","name":"Default","title":"Components/Navbar","importPath":"./src/navbar/navbar.stories.jsx","tags":["story"],"kind":"Components/Navbar","story":"Default","parameters":{"__id":"components-navbar--default","docsOnly":false,"fileName":"./src/navbar/navbar.stories.jsx"}},"example-button--docs":{"id":"example-button--docs","title":"Example/Button","name":"Docs","importPath":"./src/stories/Button.stories.js","tags":["autodocs","docs"],"storiesImports":[],"kind":"Example/Button","story":"Docs","parameters":{"__id":"example-button--docs","docsOnly":true,"fileName":"./src/stories/Button.stories.js"}},"example-button--primary":{"id":"example-button--primary","name":"Primary","title":"Example/Button","importPath":"./src/stories/Button.stories.js","tags":["autodocs","story"],"kind":"Example/Button","story":"Primary","parameters":{"__id":"example-button--primary","docsOnly":false,"fileName":"./src/stories/Button.stories.js"}},"example-button--secondary":{"id":"example-button--secondary","name":"Secondary","title":"Example/Button","importPath":"./src/stories/Button.stories.js","tags":["autodocs","story"],"kind":"Example/Button","story":"Secondary","parameters":{"__id":"example-button--secondary","docsOnly":false,"fileName":"./src/stories/Button.stories.js"}},"example-button--large":{"id":"example-button--large","name":"Large","title":"Example/Button","importPath":"./src/stories/Button.stories.js","tags":["autodocs","story"],"kind":"Example/Button","story":"Large","parameters":{"__id":"example-button--large","docsOnly":false,"fileName":"./src/stories/Button.stories.js"}},"example-button--small":{"id":"example-button--small","name":"Small","title":"Example/Button","importPath":"./src/stories/Button.stories.js","tags":["autodocs","story"],"kind":"Example/Button","story":"Small","parameters":{"__id":"example-button--small","docsOnly":false,"fileName":"./src/stories/Button.stories.js"}},"example-header--docs":{"id":"example-header--docs","title":"Example/Header","name":"Docs","importPath":"./src/stories/Header.stories.js","tags":["autodocs","docs"],"storiesImports":[],"kind":"Example/Header","story":"Docs","parameters":{"__id":"example-header--docs","docsOnly":true,"fileName":"./src/stories/Header.stories.js"}},"example-header--logged-in":{"id":"example-header--logged-in","name":"Logged In","title":"Example/Header","importPath":"./src/stories/Header.stories.js","tags":["autodocs","story"],"kind":"Example/Header","story":"Logged In","parameters":{"__id":"example-header--logged-in","docsOnly":false,"fileName":"./src/stories/Header.stories.js"}},"example-header--logged-out":{"id":"example-header--logged-out","name":"Logged Out","title":"Example/Header","importPath":"./src/stories/Header.stories.js","tags":["autodocs","story"],"kind":"Example/Header","story":"Logged Out","parameters":{"__id":"example-header--logged-out","docsOnly":false,"fileName":"./src/stories/Header.stories.js"}},"example-page--logged-out":{"id":"example-page--logged-out","name":"Logged Out","title":"Example/Page","importPath":"./src/stories/Page.stories.js","tags":["story"],"kind":"Example/Page","story":"Logged Out","parameters":{"__id":"example-page--logged-out","docsOnly":false,"fileName":"./src/stories/Page.stories.js"}},"example-page--logged-in":{"id":"example-page--logged-in","name":"Logged In","title":"Example/Page","importPath":"./src/stories/Page.stories.js","tags":["play-fn","story"],"kind":"Example/Page","story":"Logged In","parameters":{"__id":"example-page--logged-in","docsOnly":false,"fileName":"./src/stories/Page.stories.js"}},"components-timer-button--default":{"id":"components-timer-button--default","name":"Default","title":"Components/Timer Button","importPath":"./src/timerButton/timerButton.stories.jsx","tags":["story"],"kind":"Components/Timer Button","story":"Default","parameters":{"__id":"components-timer-button--default","docsOnly":false,"fileName":"./src/timerButton/timerButton.stories.jsx"}}}}
